<?xml version="1.0" encoding="UTF-8"?>
<beans xmlns:xsi="http://www.w3.org/2001/XMLSchema-instance"
	xmlns:beans="http://cxf.apache.org/configuration/beans" xmlns:context="http://www.springframework.org/schema/context"
	xmlns:jaxrs="http://cxf.apache.org/jaxrs" xmlns="http://www.springframework.org/schema/beans"
	xsi:schemaLocation="http://www.springframework.org/schema/beans http://www.springframework.org/schema/beans/spring-beans.xsd
		http://cxf.apache.org/configuration/beans http://cxf.apache.org/schemas/configuration/cxf-beans.xsd
		http://www.springframework.org/schema/context http://www.springframework.org/schema/context/spring-context-3.1.xsd
		http://cxf.apache.org/jaxrs http://cxf.apache.org/schemas/jaxrs.xsd">
		
	<bean id="executorService" class="java.util.concurrent.Executors"
		factory-method="newFixedThreadPool" destroy-method="shutdownNow">
		<constructor-arg value="2" />
	</bean>

	<bean id="asyncBus" class="com.google.common.eventbus.AsyncEventBus">
		<constructor-arg ref="executorService" />
		<constructor-arg>
			<bean class="com.appcrossings.events.EventBusExceptionHandler" />
		</constructor-arg>
	</bean>

</beans>